rjgtoys_tkthread-0.0.1-py3.8-nspkg.pth
rjgtoys/tkthread/__init__.py
rjgtoys_tkthread-0.0.1.dist-info/METADATA
rjgtoys_tkthread-0.0.1.dist-info/WHEEL
rjgtoys_tkthread-0.0.1.dist-info/namespace_packages.txt
rjgtoys_tkthread-0.0.1.dist-info/top_level.txt
rjgtoys_tkthread-0.0.1.dist-info/RECORD
