Metadata-Version: 2.1
Name: rjgtoys-tkthread
Version: 0.0.1
Summary: Enable use of threads with tkinter
Home-page: UNKNOWN
Author: Bob Gautier
Author-email: bob.gautier@gmail.com
License: UNKNOWN
Keywords: tk tkinter thread
Platform: UNKNOWN
